lwm2pdf/__init__.py
lwm2pdf/clean_html.py
lwm2pdf/filetypes.py
lwm2pdf/main.py
lwm2pdf/options.py
lwm2pdf/process_docs.py
lwm2pdf/process_options.py
lwm2pdf/process_pdf.py
lwm2pdf/themes/manuscript.css
lwm2pdf/themes/source/_basic_code_highlighter.scss
lwm2pdf/themes/source/_toc.scss
lwm2pdf/themes/source/_xrefs.scss
lwm2pdf/themes/source/manuscript.scss
lwm2pdf-0.1.4.dist-info/LICENSE.txt
lwm2pdf-0.1.4.dist-info/METADATA
lwm2pdf-0.1.4.dist-info/WHEEL
lwm2pdf-0.1.4.dist-info/entry_points.txt
lwm2pdf-0.1.4.dist-info/RECORD
